dangqu_sdk/__init__.py
dangqu_sdk/client.py
dangqu_sdk-0.5.3.dist-info/METADATA
dangqu_sdk-0.5.3.dist-info/WHEEL
dangqu_sdk-0.5.3.dist-info/top_level.txt
dangqu_sdk-0.5.3.dist-info/RECORD
