Metadata-Version: 2.1
Name: dangqu-sdk
Version: 0.5.3
Summary: dangqu sdk
Author: ZhaoHui
Author-email: myemail@example.com
Classifier: Development Status :: 3 - Alpha
Classifier: Intended Audience :: Developers
Classifier: License :: OSI Approved :: MIT License
Classifier: Programming Language :: Python :: 3
Classifier: Programming Language :: Python :: 3.7
Classifier: Programming Language :: Python :: 3.8
Classifier: Programming Language :: Python :: 3.9
Requires-Dist: requests
Requires-Dist: oauthlib
Requires-Dist: requests-oauthlib
